django_admin_action_audit-0.1.0.dist-info/licenses/LICENSE
django_admin_audit/__init__.py
django_admin_audit/admin.py
django_admin_audit/apps.py
django_admin_audit/conf.py
django_admin_audit/context.py
django_admin_audit/middleware.py
django_admin_audit/models.py
django_admin_audit/signals.py
django_admin_audit/snapshots.py
django_admin_audit/migrations/0001_initial.py
django_admin_audit/migrations/0002_add_snapshots_fields.py
django_admin_audit/migrations/__init__.py
django_admin_action_audit-0.1.0.dist-info/METADATA
django_admin_action_audit-0.1.0.dist-info/WHEEL
django_admin_action_audit-0.1.0.dist-info/top_level.txt
django_admin_action_audit-0.1.0.dist-info/RECORD
