Metadata-Version: 2.4
Name: django-admin-action-audit
Version: 0.1.0
Summary: Audit Django admin actions with request metadata.
Author: Ehsan Fouladi
License: MIT License
Project-URL: Homepage, https://github.com/ehsanfouladi/django-admin-audit
Project-URL: Issues, https://github.com/ehsanfouladi/django-admin-audit/issues
Keywords: django,admin,audit,logging
Classifier: Development Status :: 3 - Alpha
Classifier: Environment :: Web Environment
Classifier: Framework :: Django
Classifier: Framework :: Django :: 3.2
Classifier: Framework :: Django :: 4.2
Classifier: Framework :: Django :: 5.0
Classifier: Intended Audience :: Developers
Classifier: License :: OSI Approved :: MIT License
Classifier: Operating System :: OS Independent
Classifier: Programming Language :: Python
Classifier: Programming Language :: Python :: 3
Classifier: Programming Language :: Python :: 3.9
Classifier: Programming Language :: Python :: 3.10
Classifier: Programming Language :: Python :: 3.11
Classifier: Programming Language :: Python :: 3.12
Classifier: Topic :: Internet :: Log Analysis
Classifier: Topic :: Security
Classifier: Topic :: Software Development :: Libraries :: Python Modules
Requires-Python: >=3.9
License-File: LICENSE
Requires-Dist: Django>=3.2
Provides-Extra: test
Requires-Dist: pytest>=7.0; extra == "test"
Requires-Dist: pytest-django>=4.5; extra == "test"
Dynamic: license-file
